{
    "battle_number": "8890",
    "crown_players": [],
    "elapsed_time": 300,
    "estimate_gachi_power": null,
    "estimate_x_power": 2300,
    "game_mode": {
        "key": "gachi",
        "name": "ガチマッチ"
    },
    "my_team_count": 68,
    "my_team_members": [
        {
            "assist_count": 4,
            "death_count": 9,
            "game_paint_point": 1094,
            "kill_count": 10,
            "player": {
                "clothes": {
                    "brand": {
                        "frequent_skill": {
                            "id": "2",
                            "image": "/images/skill/c14f4471b26e0f918c736b5c17e03212290f4541.png",
                            "name": "インク回復力アップ"
                        },
                        "id": "10",
                        "image": "/images/brand/02286fe17bb6bc3f5f13c6b251ddc0a55c44c756.png",
                        "name": "アロメ"
                    },
                    "id": "3011",
                    "image": "/images/clothes/99e65521a7980d73a2b64b482a44d4ea0d8d1d7b.png",
                    "kind": "clothes",
                    "name": "アロメテックT ブルー",
                    "rarity": 1,
                    "thumbnail": "/images/clothes/c1d968c3167e40f30c14238196803ad7ad5cb7da.png"
                },
                "clothes_skills": {
                    "main": {
                        "id": "8",
                        "image": "/images/skill/84ab4ba1188849dff63a4314955a53ab103b47df.png",
                        "name": "復活時間短縮"
                    },
                    "subs": [
                        {
                            "id": "8",
                            "image": "/images/skill/84ab4ba1188849dff63a4314955a53ab103b47df.png",
                            "name": "復活時間短縮"
                        },
                        {
                            "id": "8",
                            "image": "/images/skill/84ab4ba1188849dff63a4314955a53ab103b47df.png",
                            "name": "復活時間短縮"
                        },
                        {
                            "id": "8",
                            "image": "/images/skill/84ab4ba1188849dff63a4314955a53ab103b47df.png",
                            "name": "復活時間短縮"
                        }
                    ]
                },
                "head": {
                    "brand": {
                        "frequent_skill": {
                            "id": "8",
                            "image": "/images/skill/84ab4ba1188849dff63a4314955a53ab103b47df.png",
                            "name": "復活時間短縮"
                        },
                        "id": "7",
                        "image": "/images/brand/8175954b5a7e02b8097dbb484c808c8f39d31f41.png",
                        "name": "ホタックス"
                    },
                    "id": "4005",
                    "image": "/images/head/6a7429ebf75973950c4b84e599d1335f7df292e9.png",
                    "kind": "head",
                    "name": "イカンカン",
                    "rarity": 0,
                    "thumbnail": "/images/head/2bd483cca35fb859fd94d6b2dad3406f42535ab1.png"
                },
                "head_skills": {
                    "main": {
                        "id": "103",
                        "image": "/images/skill/bdc5135874439cf3169d9a54b3f1fbdba3731b34.png",
                        "name": "カムバック"
                    },
                    "subs": [
                        {
                            "id": "8",
                            "image": "/images/skill/84ab4ba1188849dff63a4314955a53ab103b47df.png",
                            "name": "復活時間短縮"
                        },
                        {
                            "id": "8",
                            "image": "/images/skill/84ab4ba1188849dff63a4314955a53ab103b47df.png",
                            "name": "復活時間短縮"
                        },
                        {
                            "id": "8",
                            "image": "/images/skill/84ab4ba1188849dff63a4314955a53ab103b47df.png",
                            "name": "復活時間短縮"
                        }
                    ]
                },
                "nickname": "たこまさ",
                "player_rank": 39,
                "player_type": {
                    "species": "octolings",
                    "style": "girl"
                },
                "principal_id": "c296ef25979fc2a2",
                "shoes": {
                    "brand": {
                        "frequent_skill": {
                            "id": "5",
                            "image": "/images/skill/1378f3963526d7216ec44da35b924b81a8ff6a37.png",
                            "name": "スペシャル増加量アップ"
                        },
                        "id": "11",
                        "image": "/images/brand/eab05d2d502cf953b4ae034c87e52e8c999339d6.png",
                        "name": "ヤコ"
                    },
                    "id": "3008",
                    "image": "/images/shoes/f83b0a27745414a6d37a99db6d04c60f15accd18.png",
                    "kind": "shoes",
                    "name": "クレイジーアローズ",
                    "rarity": 1,
                    "thumbnail": "/images/shoes/0fd080a8d545e35348c440310ac4186bb65697cd.png"
                },
                "shoes_skills": {
                    "main": {
                        "id": "109",
                        "image": "/images/skill/8a3f06a972689b094f762626ff36b3db8ee545b5.png",
                        "name": "ステルスジャンプ"
                    },
                    "subs": [
                        {
                            "id": "6",
                            "image": "/images/skill/d83b962b84fcea9d02c591c296234f5de77f9682.png",
                            "name": "スペシャル減少量ダウン"
                        },
                        {
                            "id": "6",
                            "image": "/images/skill/d83b962b84fcea9d02c591c296234f5de77f9682.png",
                            "name": "スペシャル減少量ダウン"
                        },
                        {
                            "id": "9",
                            "image": "/images/skill/daf6883039afa62da91eb93eb2a40b673f10b715.png",
                            "name": "スーパージャンプ時間短縮"
                        }
                    ]
                },
                "star_rank": 2,
                "udemae": {
                    "is_x": true,
                    "name": "X",
                    "s_plus_number": null
                },
                "weapon": {
                    "id": "72",
                    "image": "/images/weapon/69cb46d940fa310937264d9cd962143e85ee633b.png",
                    "name": "プライムシューターベッチュー",
                    "special": {
                        "id": "17",
                        "image_a": "/images/special/e6f33512755e462874f57d1f02b61bb1c41ad79f.png",
                        "image_b": "/images/special/714c00b84b54d68c5e0b6da4186d41831fb4a442.png",
                        "name": "ナイスダマ"
                    },
                    "sub": {
                        "id": "0",
                        "image_a": "/images/sub/d2eaeec524d28ef315a13f8a9e11dd1039cb78aa.png",
                        "image_b": "/images/sub/b13bf755b279af83904892fae01cd98c866dfec7.png",
                        "name": "スプラッシュボム"
                    },
                    "thumbnail": "/images/weapon/54ce83bf80f87263854d3c96ebdb54f427aa0a09.png"
                }
            },
            "sort_score": 0,
            "special_count": 4
        },
        {
            "assist_count": 1,
            "death_count": 5,
            "game_paint_point": 1350,
            "kill_count": 8,
            "player": {
                "clothes": {
                    "brand": {
                        "frequent_skill": {
                            "id": "5",
                            "image": "/images/skill/1378f3963526d7216ec44da35b924b81a8ff6a37.png",
                            "name": "スペシャル増加量アップ"
                        },
                        "id": "11",
                        "image": "/images/brand/eab05d2d502cf953b4ae034c87e52e8c999339d6.png",
                        "name": "ヤコ"
                    },
                    "id": "5018",
                    "image": "/images/clothes/08ecbcd0f741b3eed1d21e117b1c4b1d299c7e54.png",
                    "kind": "clothes",
                    "name": "ヤコナイロンレトロ",
                    "rarity": 2,
                    "thumbnail": "/images/clothes/eccdc640e010a6b11490114255240ba1472e2bec.png"
                },
                "clothes_skills": {
                    "main": {
                        "id": "201",
                        "image": "/images/skill/39f3e937b709d378c178ef2bf00d9a7295b8159d.png",
                        "name": "メイン性能アップ"
                    },
                    "subs": [
                        {
                            "id": "9",
                            "image": "/images/skill/daf6883039afa62da91eb93eb2a40b673f10b715.png",
                            "name": "スーパージャンプ時間短縮"
                        },
                        {
                            "id": "201",
                            "image": "/images/skill/39f3e937b709d378c178ef2bf00d9a7295b8159d.png",
                            "name": "メイン性能アップ"
                        },
                        {
                            "id": "201",
                            "image": "/images/skill/39f3e937b709d378c178ef2bf00d9a7295b8159d.png",
                            "name": "メイン性能アップ"
                        }
                    ]
                },
                "head": {
                    "brand": {
                        "frequent_skill": {
                            "id": "8",
                            "image": "/images/skill/84ab4ba1188849dff63a4314955a53ab103b47df.png",
                            "name": "復活時間短縮"
                        },
                        "id": "7",
                        "image": "/images/brand/8175954b5a7e02b8097dbb484c808c8f39d31f41.png",
                        "name": "ホタックス"
                    },
                    "id": "2005",
                    "image": "/images/head/84ea324ce140ace9c23e72f728712d557e63644f.png",
                    "kind": "head",
                    "name": "イカノルディック",
                    "rarity": 2,
                    "thumbnail": "/images/head/39a52add9c466bc26f43fb91ea7089356e42bb04.png"
                },
                "head_skills": {
                    "main": {
                        "id": "103",
                        "image": "/images/skill/bdc5135874439cf3169d9a54b3f1fbdba3731b34.png",
                        "name": "カムバック"
                    },
                    "subs": [
                        {
                            "id": "0",
                            "image": "/images/skill/04b1de71fba1f14197b9163503955c52fd74858b.png",
                            "name": "インク効率アップ(メイン)"
                        },
                        {
                            "id": "0",
                            "image": "/images/skill/04b1de71fba1f14197b9163503955c52fd74858b.png",
                            "name": "インク効率アップ(メイン)"
                        },
                        {
                            "id": "0",
                            "image": "/images/skill/04b1de71fba1f14197b9163503955c52fd74858b.png",
                            "name": "インク効率アップ(メイン)"
                        }
                    ]
                },
                "nickname": "ぐれぼろ*YC",
                "player_rank": 59,
                "player_type": {
                    "species": "inklings",
                    "style": "girl"
                },
                "principal_id": "9b8f2dcba7e69eca",
                "shoes": {
                    "brand": {
                        "frequent_skill": {
                            "id": "5",
                            "image": "/images/skill/1378f3963526d7216ec44da35b924b81a8ff6a37.png",
                            "name": "スペシャル増加量アップ"
                        },
                        "id": "11",
                        "image": "/images/brand/eab05d2d502cf953b4ae034c87e52e8c999339d6.png",
                        "name": "ヤコ"
                    },
                    "id": "3008",
                    "image": "/images/shoes/f83b0a27745414a6d37a99db6d04c60f15accd18.png",
                    "kind": "shoes",
                    "name": "クレイジーアローズ",
                    "rarity": 1,
                    "thumbnail": "/images/shoes/0fd080a8d545e35348c440310ac4186bb65697cd.png"
                },
                "shoes_skills": {
                    "main": {
                        "id": "109",
                        "image": "/images/skill/8a3f06a972689b094f762626ff36b3db8ee545b5.png",
                        "name": "ステルスジャンプ"
                    },
                    "subs": [
                        {
                            "id": "201",
                            "image": "/images/skill/39f3e937b709d378c178ef2bf00d9a7295b8159d.png",
                            "name": "メイン性能アップ"
                        },
                        {
                            "id": "201",
                            "image": "/images/skill/39f3e937b709d378c178ef2bf00d9a7295b8159d.png",
                            "name": "メイン性能アップ"
                        },
                        {
                            "id": "0",
                            "image": "/images/skill/04b1de71fba1f14197b9163503955c52fd74858b.png",
                            "name": "インク効率アップ(メイン)"
                        }
                    ]
                },
                "star_rank": 1,
                "udemae": {
                    "is_x": true,
                    "name": "X",
                    "s_plus_number": null
                },
                "weapon": {
                    "id": "1022",
                    "image": "/images/weapon/4f011b881d26bd6c9d8c5c17f54e35fedc012bb0.png",
                    "name": "ダイナモローラーベッチュー",
                    "special": {
                        "id": "17",
                        "image_a": "/images/special/e6f33512755e462874f57d1f02b61bb1c41ad79f.png",
                        "image_b": "/images/special/714c00b84b54d68c5e0b6da4186d41831fb4a442.png",
                        "name": "ナイスダマ"
                    },
                    "sub": {
                        "id": "6",
                        "image_a": "/images/sub/46f5b9fe851d4ac8df9eb959e7270ff72526dffe.png",
                        "image_b": "/images/sub/47b6c31e712634bd793d5b920288fe7b1fb3c2bd.png",
                        "name": "スプリンクラー"
                    },
                    "thumbnail": "/images/weapon/9354e96a72e0396db6121d78d75e63bbd9bf69fc.png"
                }
            },
            "sort_score": 1,
            "special_count": 5
        },
        {
            "assist_count": 1,
            "death_count": 5,
            "game_paint_point": 915,
            "kill_count": 6,
            "player": {
                "clothes": {
                    "brand": {
                        "frequent_skill": {
                            "id": "0",
                            "image": "/images/skill/04b1de71fba1f14197b9163503955c52fd74858b.png",
                            "name": "インク効率アップ(メイン)"
                        },
                        "id": "8",
                        "image": "/images/brand/36bc10db0aa2640c87ad712fc0281515beedcca1.png",
                        "name": "ジモン"
                    },
                    "id": "2013",
                    "image": "/images/clothes/a2cc336fda6a2f7f3d4e545036fe954b24fbd535.png",
                    "kind": "clothes",
                    "name": "ゆとりボーダー ピンク",
                    "rarity": 1,
                    "thumbnail": "/images/clothes/544b679ac868bf0cd8528761683b3eb211f7aa77.png"
                },
                "clothes_skills": {
                    "main": {
                        "id": "9",
                        "image": "/images/skill/daf6883039afa62da91eb93eb2a40b673f10b715.png",
                        "name": "スーパージャンプ時間短縮"
                    },
                    "subs": [
                        {
                            "id": "0",
                            "image": "/images/skill/04b1de71fba1f14197b9163503955c52fd74858b.png",
                            "name": "インク効率アップ(メイン)"
                        },
                        {
                            "id": "2",
                            "image": "/images/skill/c14f4471b26e0f918c736b5c17e03212290f4541.png",
                            "name": "インク回復力アップ"
                        },
                        {
                            "id": "0",
                            "image": "/images/skill/04b1de71fba1f14197b9163503955c52fd74858b.png",
                            "name": "インク効率アップ(メイン)"
                        }
                    ]
                },
                "head": {
                    "brand": {
                        "frequent_skill": {
                            "id": "0",
                            "image": "/images/skill/04b1de71fba1f14197b9163503955c52fd74858b.png",
                            "name": "インク効率アップ(メイン)"
                        },
                        "id": "8",
                        "image": "/images/brand/36bc10db0aa2640c87ad712fc0281515beedcca1.png",
                        "name": "ジモン"
                    },
                    "id": "1024",
                    "image": "/images/head/615ae5728349fff04ccd4aed2f172fe6f7b27edb.png",
                    "kind": "head",
                    "name": "ハウスタグデニムCAP",
                    "rarity": 1,
                    "thumbnail": "/images/head/0f02037c3955fd3e6ecd7288aefdf7d2f1b1f6d9.png"
                },
                "head_skills": {
                    "main": {
                        "id": "5",
                        "image": "/images/skill/1378f3963526d7216ec44da35b924b81a8ff6a37.png",
                        "name": "スペシャル増加量アップ"
                    },
                    "subs": [
                        {
                            "id": "2",
                            "image": "/images/skill/c14f4471b26e0f918c736b5c17e03212290f4541.png",
                            "name": "インク回復力アップ"
                        },
                        {
                            "id": "0",
                            "image": "/images/skill/04b1de71fba1f14197b9163503955c52fd74858b.png",
                            "name": "インク効率アップ(メイン)"
                        },
                        {
                            "id": "0",
                            "image": "/images/skill/04b1de71fba1f14197b9163503955c52fd74858b.png",
                            "name": "インク効率アップ(メイン)"
                        }
                    ]
                },
                "nickname": "さらぺちちゃん",
                "player_rank": 62,
                "player_type": {
                    "species": "octolings",
                    "style": "girl"
                },
                "principal_id": "92a628ffc54484f2",
                "shoes": {
                    "brand": {
                        "frequent_skill": {
                            "id": "4",
                            "image": "/images/skill/d138c293c8ddac42fadf0e6531100a88c79c81f6.png",
                            "name": "イカダッシュ速度アップ"
                        },
                        "id": "2",
                        "image": "/images/brand/9ac5752790dd6dbdc7a427df95e1bfe89fe318e0.png",
                        "name": "クラーゲス"
                    },
                    "id": "23007",
                    "image": "/images/shoes/1122eec55c5125c2091e13d3cd6308938470ee6c.png",
                    "kind": "shoes",
                    "name": "ミッドナイトスリッポン",
                    "rarity": 2,
                    "thumbnail": "/images/shoes/4267491aebf9fd7a84d3d7654286b3197cf7bb2b.png"
                },
                "shoes_skills": {
                    "main": {
                        "id": "110",
                        "image": "/images/skill/47a74cd575b25a9de3e3592084ff3870db0cf4e0.png",
                        "name": "対物攻撃力アップ"
                    },
                    "subs": [
                        {
                            "id": "4",
                            "image": "/images/skill/d138c293c8ddac42fadf0e6531100a88c79c81f6.png",
                            "name": "イカダッシュ速度アップ"
                        },
                        {
                            "id": "7",
                            "image": "/images/skill/f20a3e85feeb6b4bb021d28059afd6265cee0b43.png",
                            "name": "スペシャル性能アップ"
                        },
                        {
                            "id": "4",
                            "image": "/images/skill/d138c293c8ddac42fadf0e6531100a88c79c81f6.png",
                            "name": "イカダッシュ速度アップ"
                        }
                    ]
                },
                "star_rank": 1,
                "udemae": {
                    "is_x": true,
                    "name": "X",
                    "s_plus_number": null
                },
                "weapon": {
                    "id": "2015",
                    "image": "/images/weapon/f4380ea765fc330a02562c442995500fb89187e0.png",
                    "name": "ヒーローチャージャー レプリカ",
                    "special": {
                        "id": "7",
                        "image_a": "/images/special/7af300fdd872feb27b3d8e68a969457fac8b3bb7.png",
                        "image_b": "/images/special/485b748720bbf809d8b28f9f4ee1a505cbcb339b.png",
                        "name": "ハイパープレッサー"
                    },
                    "sub": {
                        "id": "0",
                        "image_a": "/images/sub/d2eaeec524d28ef315a13f8a9e11dd1039cb78aa.png",
                        "image_b": "/images/sub/b13bf755b279af83904892fae01cd98c866dfec7.png",
                        "name": "スプラッシュボム"
                    },
                    "thumbnail": "/images/weapon/5a901e56b8f13eb20fee865d116199b490d1f7ae.png"
                }
            },
            "sort_score": 2,
            "special_count": 3
        }
    ],
    "my_team_result": {
        "key": "victory",
        "name": "WIN!"
    },
    "other_team_count": 38,
    "other_team_members": [
        {
            "assist_count": 2,
            "death_count": 4,
            "game_paint_point": 1653,
            "kill_count": 6,
            "player": {
                "clothes": {
                    "brand": {
                        "frequent_skill": {
                            "id": "9",
                            "image": "/images/skill/daf6883039afa62da91eb93eb2a40b673f10b715.png",
                            "name": "スーパージャンプ時間短縮"
                        },
                        "id": "1",
                        "image": "/images/brand/3d4661b3f60f4b74e9bb6760ba7397ecd2502a20.png",
                        "name": "アイロニック"
                    },
                    "id": "1040",
                    "image": "/images/clothes/d71d0028b2ba12c3e45c4b8efca24d7430985cbd.png",
                    "kind": "clothes",
                    "name": "デカロゴT ノーコン",
                    "rarity": 0,
                    "thumbnail": "/images/clothes/7a0378ef43f0469fbda72818d083893c6ff9c09e.png"
                },
                "clothes_skills": {
                    "main": {
                        "id": "0",
                        "image": "/images/skill/04b1de71fba1f14197b9163503955c52fd74858b.png",
                        "name": "インク効率アップ(メイン)"
                    },
                    "subs": [
                        {
                            "id": "2",
                            "image": "/images/skill/c14f4471b26e0f918c736b5c17e03212290f4541.png",
                            "name": "インク回復力アップ"
                        },
                        {
                            "id": "9",
                            "image": "/images/skill/daf6883039afa62da91eb93eb2a40b673f10b715.png",
                            "name": "スーパージャンプ時間短縮"
                        },
                        {
                            "id": "9",
                            "image": "/images/skill/daf6883039afa62da91eb93eb2a40b673f10b715.png",
                            "name": "スーパージャンプ時間短縮"
                        }
                    ]
                },
                "head": {
                    "brand": {
                        "frequent_skill": {
                            "id": "8",
                            "image": "/images/skill/84ab4ba1188849dff63a4314955a53ab103b47df.png",
                            "name": "復活時間短縮"
                        },
                        "id": "7",
                        "image": "/images/brand/8175954b5a7e02b8097dbb484c808c8f39d31f41.png",
                        "name": "ホタックス"
                    },
                    "id": "1026",
                    "image": "/images/head/1eaf073acff1c291bfbe4be4e46b299e6276698f.png",
                    "kind": "head",
                    "name": "ドゥーラグキャップガサネ",
                    "rarity": 2,
                    "thumbnail": "/images/head/788462faed9afa2c24e7a37717c284a3d6dc664b.png"
                },
                "head_skills": {
                    "main": {
                        "id": "201",
                        "image": "/images/skill/39f3e937b709d378c178ef2bf00d9a7295b8159d.png",
                        "name": "メイン性能アップ"
                    },
                    "subs": [
                        {
                            "id": "201",
                            "image": "/images/skill/39f3e937b709d378c178ef2bf00d9a7295b8159d.png",
                            "name": "メイン性能アップ"
                        },
                        {
                            "id": "201",
                            "image": "/images/skill/39f3e937b709d378c178ef2bf00d9a7295b8159d.png",
                            "name": "メイン性能アップ"
                        },
                        {
                            "id": "5",
                            "image": "/images/skill/1378f3963526d7216ec44da35b924b81a8ff6a37.png",
                            "name": "スペシャル増加量アップ"
                        }
                    ]
                },
                "nickname": "わるお",
                "player_rank": 99,
                "player_type": {
                    "species": "inklings",
                    "style": "boy"
                },
                "principal_id": "51314119047dc25f",
                "shoes": {
                    "brand": {
                        "frequent_skill": {
                            "id": "2",
                            "image": "/images/skill/c14f4471b26e0f918c736b5c17e03212290f4541.png",
                            "name": "インク回復力アップ"
                        },
                        "id": "10",
                        "image": "/images/brand/02286fe17bb6bc3f5f13c6b251ddc0a55c44c756.png",
                        "name": "アロメ"
                    },
                    "id": "2014",
                    "image": "/images/shoes/3e0ec9d8e0b3f2ef334eb8fd8442ba30c7357ee6.png",
                    "kind": "shoes",
                    "name": "ノリマキ750 ホワイト",
                    "rarity": 1,
                    "thumbnail": "/images/shoes/dd3194e6227cd162b32666066dda5882869d08ec.png"
                },
                "shoes_skills": {
                    "main": {
                        "id": "4",
                        "image": "/images/skill/d138c293c8ddac42fadf0e6531100a88c79c81f6.png",
                        "name": "イカダッシュ速度アップ"
                    },
                    "subs": [
                        {
                            "id": "2",
                            "image": "/images/skill/c14f4471b26e0f918c736b5c17e03212290f4541.png",
                            "name": "インク回復力アップ"
                        },
                        {
                            "id": "2",
                            "image": "/images/skill/c14f4471b26e0f918c736b5c17e03212290f4541.png",
                            "name": "インク回復力アップ"
                        },
                        {
                            "id": "2",
                            "image": "/images/skill/c14f4471b26e0f918c736b5c17e03212290f4541.png",
                            "name": "インク回復力アップ"
                        }
                    ]
                },
                "star_rank": 1,
                "udemae": {
                    "is_x": true,
                    "name": "X",
                    "s_plus_number": null
                },
                "weapon": {
                    "id": "2040",
                    "image": "/images/weapon/fd4b89e84b375f01290185f2236dbee935dd1682.png",
                    "name": "4Kスコープ",
                    "special": {
                        "id": "10",
                        "image_a": "/images/special/b07cb8cd5b8afbf509b98a9cbb768ed0f2e34898.png",
                        "image_b": "/images/special/b2ffd060612d3ed4cfa7bee583cb28d22307064a.png",
                        "name": "アメフラシ"
                    },
                    "sub": {
                        "id": "5",
                        "image_a": "/images/sub/2705be54dafc7a426539c9e8f701197b7a9373f5.png",
                        "image_b": "/images/sub/2e2d1dca678ca3b3e011c3e4620c5c0fa31a9248.png",
                        "name": "トラップ"
                    },
                    "thumbnail": "/images/weapon/42e1e9d865f3c0f23d49d05a99783d25d023b89f.png"
                }
            },
            "sort_score": 2,
            "special_count": 5
        },
        {
            "assist_count": 4,
            "death_count": 9,
            "game_paint_point": 1062,
            "kill_count": 3,
            "player": {
                "clothes": {
                    "brand": {
                        "frequent_skill": {
                            "id": "1",
                            "image": "/images/skill/da8ff08954fd5d890fc8bc4dd4cb761e2a33b703.png",
                            "name": "インク効率アップ(サブ)"
                        },
                        "id": "6",
                        "image": "/images/brand/dee59c0797a6214114e527dfa51f0dd012085172.png",
                        "name": "ホッコリー"
                    },
                    "id": "1010",
                    "image": "/images/clothes/01b7128078aa163cfcb26057e969ae6abc0cf629.png",
                    "kind": "clothes",
                    "name": "マルフグＴ",
                    "rarity": 0,
                    "thumbnail": "/images/clothes/dbc6ab09cf04d5346762e37b3f0f34ffead9b81e.png"
                },
                "clothes_skills": {
                    "main": {
                        "id": "4",
                        "image": "/images/skill/d138c293c8ddac42fadf0e6531100a88c79c81f6.png",
                        "name": "イカダッシュ速度アップ"
                    },
                    "subs": [
                        {
                            "id": "4",
                            "image": "/images/skill/d138c293c8ddac42fadf0e6531100a88c79c81f6.png",
                            "name": "イカダッシュ速度アップ"
                        },
                        {
                            "id": "4",
                            "image": "/images/skill/d138c293c8ddac42fadf0e6531100a88c79c81f6.png",
                            "name": "イカダッシュ速度アップ"
                        },
                        {
                            "id": "4",
                            "image": "/images/skill/d138c293c8ddac42fadf0e6531100a88c79c81f6.png",
                            "name": "イカダッシュ速度アップ"
                        }
                    ]
                },
                "head": {
                    "brand": {
                        "frequent_skill": {
                            "id": "1",
                            "image": "/images/skill/da8ff08954fd5d890fc8bc4dd4cb761e2a33b703.png",
                            "name": "インク効率アップ(サブ)"
                        },
                        "id": "6",
                        "image": "/images/brand/dee59c0797a6214114e527dfa51f0dd012085172.png",
                        "name": "ホッコリー"
                    },
                    "id": "8008",
                    "image": "/images/head/5f549868950f12d24b89c796862cde04f3716815.png",
                    "kind": "head",
                    "name": "マスクドホッコリー",
                    "rarity": 0,
                    "thumbnail": "/images/head/bc81db95be7406a0f4e1edd4d1f070368d6eeb01.png"
                },
                "head_skills": {
                    "main": {
                        "id": "3",
                        "image": "/images/skill/7de1bdfd875ef470b6066c17bed726b5b5113d48.png",
                        "name": "ヒト移動速度アップ"
                    },
                    "subs": [
                        {
                            "id": "3",
                            "image": "/images/skill/7de1bdfd875ef470b6066c17bed726b5b5113d48.png",
                            "name": "ヒト移動速度アップ"
                        },
                        {
                            "id": "3",
                            "image": "/images/skill/7de1bdfd875ef470b6066c17bed726b5b5113d48.png",
                            "name": "ヒト移動速度アップ"
                        },
                        {
                            "id": "3",
                            "image": "/images/skill/7de1bdfd875ef470b6066c17bed726b5b5113d48.png",
                            "name": "ヒト移動速度アップ"
                        }
                    ]
                },
                "nickname": "しーさー",
                "player_rank": 38,
                "player_type": {
                    "species": "inklings",
                    "style": "girl"
                },
                "principal_id": "2ccc51e3c9252ad5",
                "shoes": {
                    "brand": {
                        "frequent_skill": {
                            "id": "10",
                            "image": "/images/skill/34e114a50a001778a574f7061039d43e632137b7.png",
                            "name": "サブ性能アップ"
                        },
                        "id": "16",
                        "image": "/images/brand/de96243d58e41e928d30290162a6f496033da868.png",
                        "name": "エンペリー"
                    },
                    "id": "2017",
                    "image": "/images/shoes/65aeea0b4bba3b3131ce8ed87af66d22bf652a6d.png",
                    "kind": "shoes",
                    "name": "エギング4 アカクロ",
                    "rarity": 2,
                    "thumbnail": "/images/shoes/237c70d7467f31ac9810a98e34b57715473d40b4.png"
                },
                "shoes_skills": {
                    "main": {
                        "id": "5",
                        "image": "/images/skill/1378f3963526d7216ec44da35b924b81a8ff6a37.png",
                        "name": "スペシャル増加量アップ"
                    },
                    "subs": [
                        {
                            "id": "5",
                            "image": "/images/skill/1378f3963526d7216ec44da35b924b81a8ff6a37.png",
                            "name": "スペシャル増加量アップ"
                        },
                        {
                            "id": "5",
                            "image": "/images/skill/1378f3963526d7216ec44da35b924b81a8ff6a37.png",
                            "name": "スペシャル増加量アップ"
                        },
                        {
                            "id": "5",
                            "image": "/images/skill/1378f3963526d7216ec44da35b924b81a8ff6a37.png",
                            "name": "スペシャル増加量アップ"
                        }
                    ]
                },
                "star_rank": 2,
                "udemae": {
                    "is_x": true,
                    "name": "X",
                    "s_plus_number": null
                },
                "weapon": {
                    "id": "4031",
                    "image": "/images/weapon/34fd511c4ac8a10a66fe8a5f54375a14a523cfe9.png",
                    "name": "クーゲルシュライバー・ヒュー",
                    "special": {
                        "id": "10",
                        "image_a": "/images/special/b07cb8cd5b8afbf509b98a9cbb768ed0f2e34898.png",
                        "image_b": "/images/special/b2ffd060612d3ed4cfa7bee583cb28d22307064a.png",
                        "name": "アメフラシ"
                    },
                    "sub": {
                        "id": "10",
                        "image_a": "/images/sub/5a31dff440e88eb711c6e810c25b8ae3ce8e64b8.png",
                        "image_b": "/images/sub/9c61e8fb4acef3d926be099603a74a02b0976431.png",
                        "name": "ジャンプビーコン"
                    },
                    "thumbnail": "/images/weapon/0948019a40074c92affe00fd0d9d003101b6fd9d.png"
                }
            },
            "sort_score": 0,
            "special_count": 3
        },
        {
            "assist_count": 0,
            "death_count": 9,
            "game_paint_point": 934,
            "kill_count": 12,
            "player": {
                "clothes": {
                    "brand": {
                        "frequent_skill": {
                            "id": "200",
                            "image": "/images/skill/0a29f0ce326a81a5ddb3a7abab1816a25fefdc7c.png",
                            "name": "爆風ダメージ軽減・改"
                        },
                        "id": "9",
                        "image": "/images/brand/80648c6e427eae4d32677797fa1be7c0e253fda5.png",
                        "name": "シグレニ"
                    },
                    "id": "5027",
                    "image": "/images/clothes/a7c210558872c5373e5d2a20fdc463d14d7f9d63.png",
                    "kind": "clothes",
                    "name": "マウンテンノリタマゴ",
                    "rarity": 2,
                    "thumbnail": "/images/clothes/a72cc9cf22c6f6197a8906070184ea7dbf7616a1.png"
                },
                "clothes_skills": {
                    "main": {
                        "id": "6",
                        "image": "/images/skill/d83b962b84fcea9d02c591c296234f5de77f9682.png",
                        "name": "スペシャル減少量ダウン"
                    },
                    "subs": [
                        {
                            "id": "6",
                            "image": "/images/skill/d83b962b84fcea9d02c591c296234f5de77f9682.png",
                            "name": "スペシャル減少量ダウン"
                        },
                        {
                            "id": "6",
                            "image": "/images/skill/d83b962b84fcea9d02c591c296234f5de77f9682.png",
                            "name": "スペシャル減少量ダウン"
                        },
                        {
                            "id": "6",
                            "image": "/images/skill/d83b962b84fcea9d02c591c296234f5de77f9682.png",
                            "name": "スペシャル減少量ダウン"
                        }
                    ]
                },
                "head": {
                    "brand": {
                        "frequent_skill": {
                            "id": "8",
                            "image": "/images/skill/84ab4ba1188849dff63a4314955a53ab103b47df.png",
                            "name": "復活時間短縮"
                        },
                        "id": "7",
                        "image": "/images/brand/8175954b5a7e02b8097dbb484c808c8f39d31f41.png",
                        "name": "ホタックス"
                    },
                    "id": "1023",
                    "image": "/images/head/9845bc34e78c8d8bced49d240e3ab66e4ce74e2b.png",
                    "kind": "head",
                    "name": "クラゲーダーキャップ",
                    "rarity": 2,
                    "thumbnail": "/images/head/b247ff650828d5ec5286eacdbd1cc11b4000b482.png"
                },
                "head_skills": {
                    "main": {
                        "id": "1",
                        "image": "/images/skill/da8ff08954fd5d890fc8bc4dd4cb761e2a33b703.png",
                        "name": "インク効率アップ(サブ)"
                    },
                    "subs": [
                        {
                            "id": "1",
                            "image": "/images/skill/da8ff08954fd5d890fc8bc4dd4cb761e2a33b703.png",
                            "name": "インク効率アップ(サブ)"
                        },
                        {
                            "id": "1",
                            "image": "/images/skill/da8ff08954fd5d890fc8bc4dd4cb761e2a33b703.png",
                            "name": "インク効率アップ(サブ)"
                        },
                        {
                            "id": "1",
                            "image": "/images/skill/da8ff08954fd5d890fc8bc4dd4cb761e2a33b703.png",
                            "name": "インク効率アップ(サブ)"
                        }
                    ]
                },
                "nickname": "Xene:D",
                "player_rank": 89,
                "player_type": {
                    "species": "octolings",
                    "style": "girl"
                },
                "principal_id": "aed34d1a6494586e",
                "shoes": {
                    "brand": {
                        "id": "97",
                        "image": "/images/brand/ec85f17c315e0a1ea4dee55041fd30a88d6aba93.png",
                        "name": "クマサン商会"
                    },
                    "id": "21006",
                    "image": "/images/shoes/995412c71614020526595d9dbc64bd593d780fcf.png",
                    "kind": "shoes",
                    "name": "バンカラコロン",
                    "rarity": 2,
                    "thumbnail": "/images/shoes/4e5dd5c86cf73572c0453dd0f244083c1e2079bf.png"
                },
                "shoes_skills": {
                    "main": {
                        "id": "6",
                        "image": "/images/skill/d83b962b84fcea9d02c591c296234f5de77f9682.png",
                        "name": "スペシャル減少量ダウン"
                    },
                    "subs": [
                        {
                            "id": "1",
                            "image": "/images/skill/da8ff08954fd5d890fc8bc4dd4cb761e2a33b703.png",
                            "name": "インク効率アップ(サブ)"
                        },
                        {
                            "id": "6",
                            "image": "/images/skill/d83b962b84fcea9d02c591c296234f5de77f9682.png",
                            "name": "スペシャル減少量ダウン"
                        },
                        {
                            "id": "1",
                            "image": "/images/skill/da8ff08954fd5d890fc8bc4dd4cb761e2a33b703.png",
                            "name": "インク効率アップ(サブ)"
                        }
                    ]
                },
                "star_rank": 1,
                "udemae": {
                    "is_x": true,
                    "name": "X",
                    "s_plus_number": null
                },
                "weapon": {
                    "id": "230",
                    "image": "/images/weapon/2b684d81508ca5286060767e29dd81ca38303f43.png",
                    "name": "クラッシュブラスター",
                    "special": {
                        "id": "7",
                        "image_a": "/images/special/7af300fdd872feb27b3d8e68a969457fac8b3bb7.png",
                        "image_b": "/images/special/485b748720bbf809d8b28f9f4ee1a505cbcb339b.png",
                        "name": "ハイパープレッサー"
                    },
                    "sub": {
                        "id": "0",
                        "image_a": "/images/sub/d2eaeec524d28ef315a13f8a9e11dd1039cb78aa.png",
                        "image_b": "/images/sub/b13bf755b279af83904892fae01cd98c866dfec7.png",
                        "name": "スプラッシュボム"
                    },
                    "thumbnail": "/images/weapon/34f78531f33c2952f9522eeb550838070ecde432.png"
                }
            },
            "sort_score": 3,
            "special_count": 3
        },
        {
            "assist_count": 1,
            "death_count": 6,
            "game_paint_point": 1162,
            "kill_count": 3,
            "player": {
                "clothes": {
                    "brand": {
                        "frequent_skill": {
                            "id": "5",
                            "image": "/images/skill/1378f3963526d7216ec44da35b924b81a8ff6a37.png",
                            "name": "スペシャル増加量アップ"
                        },
                        "id": "11",
                        "image": "/images/brand/eab05d2d502cf953b4ae034c87e52e8c999339d6.png",
                        "name": "ヤコ"
                    },
                    "id": "5018",
                    "image": "/images/clothes/08ecbcd0f741b3eed1d21e117b1c4b1d299c7e54.png",
                    "kind": "clothes",
                    "name": "ヤコナイロンレトロ",
                    "rarity": 2,
                    "thumbnail": "/images/clothes/eccdc640e010a6b11490114255240ba1472e2bec.png"
                },
                "clothes_skills": {
                    "main": {
                        "id": "201",
                        "image": "/images/skill/39f3e937b709d378c178ef2bf00d9a7295b8159d.png",
                        "name": "メイン性能アップ"
                    },
                    "subs": [
                        {
                            "id": "201",
                            "image": "/images/skill/39f3e937b709d378c178ef2bf00d9a7295b8159d.png",
                            "name": "メイン性能アップ"
                        },
                        {
                            "id": "201",
                            "image": "/images/skill/39f3e937b709d378c178ef2bf00d9a7295b8159d.png",
                            "name": "メイン性能アップ"
                        },
                        {
                            "id": "4",
                            "image": "/images/skill/d138c293c8ddac42fadf0e6531100a88c79c81f6.png",
                            "name": "イカダッシュ速度アップ"
                        }
                    ]
                },
                "head": {
                    "brand": {
                        "id": "97",
                        "image": "/images/brand/ec85f17c315e0a1ea4dee55041fd30a88d6aba93.png",
                        "name": "クマサン商会"
                    },
                    "id": "21005",
                    "image": "/images/head/dda09e3858519df0080eba6da78dc84d6824df14.png",
                    "kind": "head",
                    "name": "レジェンドのぼうし",
                    "rarity": 2,
                    "thumbnail": "/images/head/b74761d9715ba7f8c0726b14de0c4cef77e5fc47.png"
                },
                "head_skills": {
                    "main": {
                        "id": "0",
                        "image": "/images/skill/04b1de71fba1f14197b9163503955c52fd74858b.png",
                        "name": "インク効率アップ(メイン)"
                    },
                    "subs": [
                        {
                            "id": "1",
                            "image": "/images/skill/da8ff08954fd5d890fc8bc4dd4cb761e2a33b703.png",
                            "name": "インク効率アップ(サブ)"
                        },
                        {
                            "id": "1",
                            "image": "/images/skill/da8ff08954fd5d890fc8bc4dd4cb761e2a33b703.png",
                            "name": "インク効率アップ(サブ)"
                        },
                        {
                            "id": "201",
                            "image": "/images/skill/39f3e937b709d378c178ef2bf00d9a7295b8159d.png",
                            "name": "メイン性能アップ"
                        }
                    ]
                },
                "nickname": "イクラのあじ!",
                "player_rank": 18,
                "player_type": {
                    "species": "inklings",
                    "style": "girl"
                },
                "principal_id": "f5a2fe1a84d1e7bf",
                "shoes": {
                    "brand": {
                        "id": "97",
                        "image": "/images/brand/ec85f17c315e0a1ea4dee55041fd30a88d6aba93.png",
                        "name": "クマサン商会"
                    },
                    "id": "21001",
                    "image": "/images/shoes/206d437ad123324371028fe277a53ad1e25c61d1.png",
                    "kind": "shoes",
                    "name": "マッドラバー",
                    "rarity": 2,
                    "thumbnail": "/images/shoes/0d88119230d2302ce87ad723ae342091205d9bd5.png"
                },
                "shoes_skills": {
                    "main": {
                        "id": "4",
                        "image": "/images/skill/d138c293c8ddac42fadf0e6531100a88c79c81f6.png",
                        "name": "イカダッシュ速度アップ"
                    },
                    "subs": [
                        {
                            "id": "4",
                            "image": "/images/skill/d138c293c8ddac42fadf0e6531100a88c79c81f6.png",
                            "name": "イカダッシュ速度アップ"
                        },
                        {
                            "id": "5",
                            "image": "/images/skill/1378f3963526d7216ec44da35b924b81a8ff6a37.png",
                            "name": "スペシャル増加量アップ"
                        },
                        {
                            "id": "0",
                            "image": "/images/skill/04b1de71fba1f14197b9163503955c52fd74858b.png",
                            "name": "インク効率アップ(メイン)"
                        }
                    ]
                },
                "star_rank": 2,
                "udemae": {
                    "is_x": true,
                    "name": "X",
                    "s_plus_number": null
                },
                "weapon": {
                    "id": "51",
                    "image": "/images/weapon/2c25adafa26ea3bb287b0aa21d02aaa856e19321.png",
                    "name": ".52ガロンデコ",
                    "special": {
                        "id": "7",
                        "image_a": "/images/special/7af300fdd872feb27b3d8e68a969457fac8b3bb7.png",
                        "image_b": "/images/special/485b748720bbf809d8b28f9f4ee1a505cbcb339b.png",
                        "name": "ハイパープレッサー"
                    },
                    "sub": {
                        "id": "3",
                        "image_a": "/images/sub/e398a9e0360f048b6a0c4c3c1e89211cca96577f.png",
                        "image_b": "/images/sub/2b5797c0ad847a54b9bd8168e75050484919d373.png",
                        "name": "カーリングボム"
                    },
                    "thumbnail": "/images/weapon/7c1f6652d03aeb89872cb48ec355205232926869.png"
                }
            },
            "sort_score": 1,
            "special_count": 5
        }
    ],
    "other_team_result": {
        "key": "defeat",
        "name": "LOSE…"
    },
    "player_rank": 44,
    "player_result": {
        "assist_count": 6,
        "death_count": 5,
        "game_paint_point": 1393,
        "kill_count": 4,
        "player": {
            "clothes": {
                "brand": {
                    "frequent_skill": {
                        "id": "9",
                        "image": "/images/skill/daf6883039afa62da91eb93eb2a40b673f10b715.png",
                        "name": "スーパージャンプ時間短縮"
                    },
                    "id": "1",
                    "image": "/images/brand/3d4661b3f60f4b74e9bb6760ba7397ecd2502a20.png",
                    "name": "アイロニック"
                },
                "id": "1031",
                "image": "/images/clothes/19f7a97d7c979843fcb94935707e0b76ca323643.png",
                "kind": "clothes",
                "name": "デカロゴＴ シロ",
                "rarity": 0,
                "thumbnail": "/images/clothes/28d03e319cb5086d23ba8d9844241a18cd388a90.png"
            },
            "clothes_skills": {
                "main": {
                    "id": "11",
                    "image": "/images/skill/33087a476135074af856151a89a6fe4d1d3a996e.png",
                    "name": "相手インク影響軽減"
                },
                "subs": [
                    {
                        "id": "3",
                        "image": "/images/skill/7de1bdfd875ef470b6066c17bed726b5b5113d48.png",
                        "name": "ヒト移動速度アップ"
                    },
                    {
                        "id": "3",
                        "image": "/images/skill/7de1bdfd875ef470b6066c17bed726b5b5113d48.png",
                        "name": "ヒト移動速度アップ"
                    },
                    {
                        "id": "3",
                        "image": "/images/skill/7de1bdfd875ef470b6066c17bed726b5b5113d48.png",
                        "name": "ヒト移動速度アップ"
                    }
                ]
            },
            "head": {
                "brand": {
                    "id": "98",
                    "image": "/images/brand/047cbc2f0674eeb4796efb3b6ec1b710b22d07e7.png",
                    "name": "アタリメイド"
                },
                "id": "27106",
                "image": "/images/head/fb4324a76a864904c89f63d2860193ef03fdfa22.png",
                "kind": "head",
                "name": "グランパなアタマ",
                "rarity": 1,
                "thumbnail": "/images/head/77f1673b278905c70e499ac8c1b5f70ce5846678.png"
            },
            "head_skills": {
                "main": {
                    "id": "103",
                    "image": "/images/skill/bdc5135874439cf3169d9a54b3f1fbdba3731b34.png",
                    "name": "カムバック"
                },
                "subs": [
                    {
                        "id": "10",
                        "image": "/images/skill/34e114a50a001778a574f7061039d43e632137b7.png",
                        "name": "サブ性能アップ"
                    },
                    {
                        "id": "200",
                        "image": "/images/skill/0a29f0ce326a81a5ddb3a7abab1816a25fefdc7c.png",
                        "name": "爆風ダメージ軽減・改"
                    },
                    {
                        "id": "10",
                        "image": "/images/skill/34e114a50a001778a574f7061039d43e632137b7.png",
                        "name": "サブ性能アップ"
                    }
                ]
            },
            "nickname": "ちゅーたな",
            "player_rank": 44,
            "player_type": {
                "species": "octolings",
                "style": "girl"
            },
            "principal_id": "fb9a41e92d348bb7",
            "shoes": {
                "brand": {
                    "frequent_skill": {
                        "id": "4",
                        "image": "/images/skill/d138c293c8ddac42fadf0e6531100a88c79c81f6.png",
                        "name": "イカダッシュ速度アップ"
                    },
                    "id": "2",
                    "image": "/images/brand/9ac5752790dd6dbdc7a427df95e1bfe89fe318e0.png",
                    "name": "クラーゲス"
                },
                "id": "4000",
                "image": "/images/shoes/c04a1ffdbea45f728f65fca0ca7142cd38cedfe8.png",
                "kind": "shoes",
                "name": "オイスタークロッグ",
                "rarity": 0,
                "thumbnail": "/images/shoes/19feeb268c95dae1e47b53617e5784809c571a10.png"
            },
            "shoes_skills": {
                "main": {
                    "id": "109",
                    "image": "/images/skill/8a3f06a972689b094f762626ff36b3db8ee545b5.png",
                    "name": "ステルスジャンプ"
                },
                "subs": [
                    {
                        "id": "8",
                        "image": "/images/skill/84ab4ba1188849dff63a4314955a53ab103b47df.png",
                        "name": "復活時間短縮"
                    },
                    {
                        "id": "8",
                        "image": "/images/skill/84ab4ba1188849dff63a4314955a53ab103b47df.png",
                        "name": "復活時間短縮"
                    },
                    {
                        "id": "8",
                        "image": "/images/skill/84ab4ba1188849dff63a4314955a53ab103b47df.png",
                        "name": "復活時間短縮"
                    }
                ]
            },
            "star_rank": 1,
            "udemae": {
                "is_number_reached": true,
                "is_x": true,
                "name": "X",
                "number": 128,
                "s_plus_number": null
            },
            "weapon": {
                "id": "60",
                "image": "/images/weapon/1f2b1db5917ef7a4e62f0e15b8805275e33f2179.png",
                "name": "N-ZAP85",
                "special": {
                    "id": "1",
                    "image_a": "/images/special/abe458a7d13d855f1b27135ccf3e96f46f1f3d10.png",
                    "image_b": "/images/special/415bf85acb0b0dcc478316332fe86efb1fe4f203.png",
                    "name": "インクアーマー"
                },
                "sub": {
                    "id": "1",
                    "image_a": "/images/sub/79ec06c8afca6af0e14da4d9941706bb15f9927e.png",
                    "image_b": "/images/sub/9d6336b855940f6c8fc82979a972f9f3381c0e65.png",
                    "name": "キューバンボム"
                },
                "thumbnail": "/images/weapon/fdcd7cbe806eb84df374ea8f7e074ac9637d4762.png"
            }
        },
        "sort_score": 3,
        "special_count": 6
    },
    "rank": null,
    "rule": {
        "key": "tower_control",
        "multiline_name": "ガチ\nヤグラ",
        "name": "ガチヤグラ"
    },
    "stage": {
        "id": "18",
        "image": "/images/stage/8cab733d543efc9dd561bfcc9edac52594e62522.png",
        "name": "アジフライスタジアム"
    },
    "star_rank": 1,
    "start_time": 1573284902,
    "type": "gachi",
    "udemae": {
        "is_number_reached": true,
        "is_x": true,
        "name": "X",
        "number": 128,
        "s_plus_number": null
    },
    "weapon_paint_point": 3094996,
    "x_power": 2337.7
}