{
    "battle_number": "8879",
    "crown_players": [],
    "elapsed_time": 313,
    "estimate_gachi_power": null,
    "estimate_x_power": 2340,
    "game_mode": {
        "key": "gachi",
        "name": "ガチマッチ"
    },
    "my_team_count": 72,
    "my_team_members": [
        {
            "assist_count": 3,
            "death_count": 8,
            "game_paint_point": 878,
            "kill_count": 10,
            "player": {
                "clothes": {
                    "brand": {
                        "frequent_skill": {
                            "id": "4",
                            "image": "/images/skill/d138c293c8ddac42fadf0e6531100a88c79c81f6.png",
                            "name": "イカダッシュ速度アップ"
                        },
                        "id": "2",
                        "image": "/images/brand/9ac5752790dd6dbdc7a427df95e1bfe89fe318e0.png",
                        "name": "クラーゲス"
                    },
                    "id": "8018",
                    "image": "/images/clothes/f7e0b134df34ae746aec9b19d1daa4147f2e2448.png",
                    "kind": "clothes",
                    "name": "タコボウラーシャツ",
                    "rarity": 1,
                    "thumbnail": "/images/clothes/b47996adb2291e1a8750b527046f3b33b243f047.png"
                },
                "clothes_skills": {
                    "main": {
                        "id": "104",
                        "image": "/images/skill/f0a99d1ab1a765b992b79610ebdc25b69d88fae9.png",
                        "name": "イカニンジャ"
                    },
                    "subs": [
                        {
                            "id": "4",
                            "image": "/images/skill/d138c293c8ddac42fadf0e6531100a88c79c81f6.png",
                            "name": "イカダッシュ速度アップ"
                        },
                        {
                            "id": "4",
                            "image": "/images/skill/d138c293c8ddac42fadf0e6531100a88c79c81f6.png",
                            "name": "イカダッシュ速度アップ"
                        },
                        {
                            "id": "4",
                            "image": "/images/skill/d138c293c8ddac42fadf0e6531100a88c79c81f6.png",
                            "name": "イカダッシュ速度アップ"
                        }
                    ]
                },
                "head": {
                    "brand": {
                        "frequent_skill": {
                            "id": "11",
                            "image": "/images/skill/33087a476135074af856151a89a6fe4d1d3a996e.png",
                            "name": "相手インク影響軽減"
                        },
                        "id": "0",
                        "image": "/images/brand/5547e529d160b188d104e3b68ff4b7566eab9771.png",
                        "name": "バトロイカ"
                    },
                    "id": "1",
                    "image": "/images/head/47f5724d202bff87b96c8fcbe398c9dcd5c7783c.png",
                    "kind": "head",
                    "name": "ヘッドバンド ホワイト",
                    "rarity": 0,
                    "thumbnail": "/images/head/d018a3ae596a2e9df77eaac461f63da3f21335c8.png"
                },
                "head_skills": {
                    "main": {
                        "id": "2",
                        "image": "/images/skill/c14f4471b26e0f918c736b5c17e03212290f4541.png",
                        "name": "インク回復力アップ"
                    },
                    "subs": [
                        {
                            "id": "2",
                            "image": "/images/skill/c14f4471b26e0f918c736b5c17e03212290f4541.png",
                            "name": "インク回復力アップ"
                        },
                        {
                            "id": "2",
                            "image": "/images/skill/c14f4471b26e0f918c736b5c17e03212290f4541.png",
                            "name": "インク回復力アップ"
                        },
                        {
                            "id": "2",
                            "image": "/images/skill/c14f4471b26e0f918c736b5c17e03212290f4541.png",
                            "name": "インク回復力アップ"
                        }
                    ]
                },
                "nickname": "Lα#ƒmalinƒ",
                "player_rank": 56,
                "player_type": {
                    "species": "octolings",
                    "style": "girl"
                },
                "principal_id": "ccb2a64ccbf370b1",
                "shoes": {
                    "brand": {
                        "frequent_skill": {
                            "id": "9",
                            "image": "/images/skill/daf6883039afa62da91eb93eb2a40b673f10b715.png",
                            "name": "スーパージャンプ時間短縮"
                        },
                        "id": "1",
                        "image": "/images/brand/3d4661b3f60f4b74e9bb6760ba7397ecd2502a20.png",
                        "name": "アイロニック"
                    },
                    "id": "2006",
                    "image": "/images/shoes/3bbeed1bf56620ec813925bb07d3e490c6d52eb7.png",
                    "kind": "shoes",
                    "name": "シーホースHi ゴールド",
                    "rarity": 2,
                    "thumbnail": "/images/shoes/cdd92036177a047dad52a4f2a3b6d86ec9d8abf7.png"
                },
                "shoes_skills": {
                    "main": {
                        "id": "3",
                        "image": "/images/skill/7de1bdfd875ef470b6066c17bed726b5b5113d48.png",
                        "name": "ヒト移動速度アップ"
                    },
                    "subs": [
                        {
                            "id": "3",
                            "image": "/images/skill/7de1bdfd875ef470b6066c17bed726b5b5113d48.png",
                            "name": "ヒト移動速度アップ"
                        },
                        {
                            "id": "3",
                            "image": "/images/skill/7de1bdfd875ef470b6066c17bed726b5b5113d48.png",
                            "name": "ヒト移動速度アップ"
                        },
                        {
                            "id": "3",
                            "image": "/images/skill/7de1bdfd875ef470b6066c17bed726b5b5113d48.png",
                            "name": "ヒト移動速度アップ"
                        }
                    ]
                },
                "star_rank": 3,
                "udemae": {
                    "is_x": true,
                    "name": "X",
                    "s_plus_number": null
                },
                "weapon": {
                    "id": "231",
                    "image": "/images/weapon/03300b6db070d0cdf00f8f305b73f53738fe138d.png",
                    "name": "クラッシュブラスターネオ",
                    "special": {
                        "id": "0",
                        "image_a": "/images/special/e395a50d51459dcee4db62d8d1fbc4bb263bc326.png",
                        "image_b": "/images/special/4819d9d318668bdd5dab248a23397ec351bc5c60.png",
                        "name": "マルチミサイル"
                    },
                    "sub": {
                        "id": "3",
                        "image_a": "/images/sub/e398a9e0360f048b6a0c4c3c1e89211cca96577f.png",
                        "image_b": "/images/sub/2b5797c0ad847a54b9bd8168e75050484919d373.png",
                        "name": "カーリングボム"
                    },
                    "thumbnail": "/images/weapon/9176035499629be618544bb8313044f6bb3b1344.png"
                }
            },
            "sort_score": 0,
            "special_count": 3
        },
        {
            "assist_count": 2,
            "death_count": 8,
            "game_paint_point": 1173,
            "kill_count": 5,
            "player": {
                "clothes": {
                    "brand": {
                        "frequent_skill": {
                            "id": "11",
                            "image": "/images/skill/33087a476135074af856151a89a6fe4d1d3a996e.png",
                            "name": "相手インク影響軽減"
                        },
                        "id": "0",
                        "image": "/images/brand/5547e529d160b188d104e3b68ff4b7566eab9771.png",
                        "name": "バトロイカ"
                    },
                    "id": "1035",
                    "image": "/images/clothes/9a6b121f9fae78fec165b103b1ebf66030bccd13.png",
                    "kind": "clothes",
                    "name": "イカホワイトV",
                    "rarity": 1,
                    "thumbnail": "/images/clothes/f02f336c5bb1a0d733abbd3fdc37f98e192b3e33.png"
                },
                "clothes_skills": {
                    "main": {
                        "id": "3",
                        "image": "/images/skill/7de1bdfd875ef470b6066c17bed726b5b5113d48.png",
                        "name": "ヒト移動速度アップ"
                    },
                    "subs": [
                        {
                            "id": "11",
                            "image": "/images/skill/33087a476135074af856151a89a6fe4d1d3a996e.png",
                            "name": "相手インク影響軽減"
                        },
                        {
                            "id": "11",
                            "image": "/images/skill/33087a476135074af856151a89a6fe4d1d3a996e.png",
                            "name": "相手インク影響軽減"
                        },
                        {
                            "id": "11",
                            "image": "/images/skill/33087a476135074af856151a89a6fe4d1d3a996e.png",
                            "name": "相手インク影響軽減"
                        }
                    ]
                },
                "head": {
                    "brand": {
                        "frequent_skill": {
                            "id": "6",
                            "image": "/images/skill/d83b962b84fcea9d02c591c296234f5de77f9682.png",
                            "name": "スペシャル減少量ダウン"
                        },
                        "id": "4",
                        "image": "/images/brand/f3d01187fd633e7d48d9e4e16ef31da73279293c.png",
                        "name": "エゾッコ"
                    },
                    "id": "3012",
                    "image": "/images/head/3186344c270ce80a43ada98bd1b17e63bdaff128.png",
                    "kind": "head",
                    "name": "ダブルエッグサングラス",
                    "rarity": 1,
                    "thumbnail": "/images/head/8408e19f4f9fb3293e083c5bac28da60df430143.png"
                },
                "head_skills": {
                    "main": {
                        "id": "3",
                        "image": "/images/skill/7de1bdfd875ef470b6066c17bed726b5b5113d48.png",
                        "name": "ヒト移動速度アップ"
                    },
                    "subs": [
                        {
                            "id": "3",
                            "image": "/images/skill/7de1bdfd875ef470b6066c17bed726b5b5113d48.png",
                            "name": "ヒト移動速度アップ"
                        },
                        {
                            "id": "3",
                            "image": "/images/skill/7de1bdfd875ef470b6066c17bed726b5b5113d48.png",
                            "name": "ヒト移動速度アップ"
                        },
                        {
                            "id": "3",
                            "image": "/images/skill/7de1bdfd875ef470b6066c17bed726b5b5113d48.png",
                            "name": "ヒト移動速度アップ"
                        }
                    ]
                },
                "nickname": "せーま",
                "player_rank": 63,
                "player_type": {
                    "species": "inklings",
                    "style": "boy"
                },
                "principal_id": "8fcb2392d566643d",
                "shoes": {
                    "brand": {
                        "frequent_skill": {
                            "id": "4",
                            "image": "/images/skill/d138c293c8ddac42fadf0e6531100a88c79c81f6.png",
                            "name": "イカダッシュ速度アップ"
                        },
                        "id": "2",
                        "image": "/images/brand/9ac5752790dd6dbdc7a427df95e1bfe89fe318e0.png",
                        "name": "クラーゲス"
                    },
                    "id": "4003",
                    "image": "/images/shoes/a6e3f883201f1a76d4debbef9c8b767cdf9f70f8.png",
                    "kind": "shoes",
                    "name": "アケビコンフォート",
                    "rarity": 1,
                    "thumbnail": "/images/shoes/3251824645a4ec44e464c6dee636471917752e6d.png"
                },
                "shoes_skills": {
                    "main": {
                        "id": "110",
                        "image": "/images/skill/47a74cd575b25a9de3e3592084ff3870db0cf4e0.png",
                        "name": "対物攻撃力アップ"
                    },
                    "subs": [
                        {
                            "id": "4",
                            "image": "/images/skill/d138c293c8ddac42fadf0e6531100a88c79c81f6.png",
                            "name": "イカダッシュ速度アップ"
                        },
                        {
                            "id": "11",
                            "image": "/images/skill/33087a476135074af856151a89a6fe4d1d3a996e.png",
                            "name": "相手インク影響軽減"
                        },
                        {
                            "id": "4",
                            "image": "/images/skill/d138c293c8ddac42fadf0e6531100a88c79c81f6.png",
                            "name": "イカダッシュ速度アップ"
                        }
                    ]
                },
                "star_rank": 2,
                "udemae": {
                    "is_x": true,
                    "name": "X",
                    "s_plus_number": null
                },
                "weapon": {
                    "id": "4031",
                    "image": "/images/weapon/34fd511c4ac8a10a66fe8a5f54375a14a523cfe9.png",
                    "name": "クーゲルシュライバー・ヒュー",
                    "special": {
                        "id": "10",
                        "image_a": "/images/special/b07cb8cd5b8afbf509b98a9cbb768ed0f2e34898.png",
                        "image_b": "/images/special/b2ffd060612d3ed4cfa7bee583cb28d22307064a.png",
                        "name": "アメフラシ"
                    },
                    "sub": {
                        "id": "10",
                        "image_a": "/images/sub/5a31dff440e88eb711c6e810c25b8ae3ce8e64b8.png",
                        "image_b": "/images/sub/9c61e8fb4acef3d926be099603a74a02b0976431.png",
                        "name": "ジャンプビーコン"
                    },
                    "thumbnail": "/images/weapon/0948019a40074c92affe00fd0d9d003101b6fd9d.png"
                }
            },
            "sort_score": 3,
            "special_count": 1
        },
        {
            "assist_count": 4,
            "death_count": 6,
            "game_paint_point": 1229,
            "kill_count": 11,
            "player": {
                "clothes": {
                    "brand": {
                        "frequent_skill": {
                            "id": "11",
                            "image": "/images/skill/33087a476135074af856151a89a6fe4d1d3a996e.png",
                            "name": "相手インク影響軽減"
                        },
                        "id": "0",
                        "image": "/images/brand/5547e529d160b188d104e3b68ff4b7566eab9771.png",
                        "name": "バトロイカ"
                    },
                    "id": "1052",
                    "image": "/images/clothes/27dcc690e7fd311b7be3429001a4aac8a4e88ba3.png",
                    "kind": "clothes",
                    "name": "リーグT",
                    "rarity": 1,
                    "thumbnail": "/images/clothes/5e35ce167739ee4c2b144e9e66f8a27d5d45f2da.png"
                },
                "clothes_skills": {
                    "main": {
                        "id": "7",
                        "image": "/images/skill/f20a3e85feeb6b4bb021d28059afd6265cee0b43.png",
                        "name": "スペシャル性能アップ"
                    },
                    "subs": [
                        {
                            "id": "11",
                            "image": "/images/skill/33087a476135074af856151a89a6fe4d1d3a996e.png",
                            "name": "相手インク影響軽減"
                        },
                        {
                            "id": "11",
                            "image": "/images/skill/33087a476135074af856151a89a6fe4d1d3a996e.png",
                            "name": "相手インク影響軽減"
                        },
                        {
                            "id": "6",
                            "image": "/images/skill/d83b962b84fcea9d02c591c296234f5de77f9682.png",
                            "name": "スペシャル減少量ダウン"
                        }
                    ]
                },
                "head": {
                    "brand": {
                        "frequent_skill": {
                            "id": "7",
                            "image": "/images/skill/f20a3e85feeb6b4bb021d28059afd6265cee0b43.png",
                            "name": "スペシャル性能アップ"
                        },
                        "id": "5",
                        "image": "/images/brand/b38b99b3358f587efd1613b72a72c9ca9f81f406.png",
                        "name": "フォーリマ"
                    },
                    "id": "2004",
                    "image": "/images/head/04e306cba184fbf94a811f815f3faeedf62352e4.png",
                    "kind": "head",
                    "name": "モンゴウベレー",
                    "rarity": 2,
                    "thumbnail": "/images/head/3c65e6845ebfb45093326c592fd084f4b89ffdbd.png"
                },
                "head_skills": {
                    "main": {
                        "id": "103",
                        "image": "/images/skill/bdc5135874439cf3169d9a54b3f1fbdba3731b34.png",
                        "name": "カムバック"
                    },
                    "subs": [
                        {
                            "id": "7",
                            "image": "/images/skill/f20a3e85feeb6b4bb021d28059afd6265cee0b43.png",
                            "name": "スペシャル性能アップ"
                        },
                        {
                            "id": "7",
                            "image": "/images/skill/f20a3e85feeb6b4bb021d28059afd6265cee0b43.png",
                            "name": "スペシャル性能アップ"
                        },
                        {
                            "id": "9",
                            "image": "/images/skill/daf6883039afa62da91eb93eb2a40b673f10b715.png",
                            "name": "スーパージャンプ時間短縮"
                        }
                    ]
                },
                "nickname": "かららぬこてぃー",
                "player_rank": 49,
                "player_type": {
                    "species": "inklings",
                    "style": "girl"
                },
                "principal_id": "ad291d86329b4e7a",
                "shoes": {
                    "brand": {
                        "frequent_skill": {
                            "id": "4",
                            "image": "/images/skill/d138c293c8ddac42fadf0e6531100a88c79c81f6.png",
                            "name": "イカダッシュ速度アップ"
                        },
                        "id": "2",
                        "image": "/images/brand/9ac5752790dd6dbdc7a427df95e1bfe89fe318e0.png",
                        "name": "クラーゲス"
                    },
                    "id": "4003",
                    "image": "/images/shoes/a6e3f883201f1a76d4debbef9c8b767cdf9f70f8.png",
                    "kind": "shoes",
                    "name": "アケビコンフォート",
                    "rarity": 1,
                    "thumbnail": "/images/shoes/3251824645a4ec44e464c6dee636471917752e6d.png"
                },
                "shoes_skills": {
                    "main": {
                        "id": "110",
                        "image": "/images/skill/47a74cd575b25a9de3e3592084ff3870db0cf4e0.png",
                        "name": "対物攻撃力アップ"
                    },
                    "subs": [
                        {
                            "id": "2",
                            "image": "/images/skill/c14f4471b26e0f918c736b5c17e03212290f4541.png",
                            "name": "インク回復力アップ"
                        },
                        {
                            "id": "2",
                            "image": "/images/skill/c14f4471b26e0f918c736b5c17e03212290f4541.png",
                            "name": "インク回復力アップ"
                        },
                        {
                            "id": "200",
                            "image": "/images/skill/0a29f0ce326a81a5ddb3a7abab1816a25fefdc7c.png",
                            "name": "爆風ダメージ軽減・改"
                        }
                    ]
                },
                "star_rank": 2,
                "udemae": {
                    "is_x": true,
                    "name": "X",
                    "s_plus_number": null
                },
                "weapon": {
                    "id": "71",
                    "image": "/images/weapon/2568ff485aa5ac6636ff5d1f78af4b94f86a3e1a.png",
                    "name": "プライムシューターコラボ",
                    "special": {
                        "id": "12",
                        "image_a": "/images/special/f49b0c33e1e25853a15dfc6a6c95705e8d290741.png",
                        "image_b": "/images/special/7cebdb0c336b64b829a1cfae2d40c0c4cb24a897.png",
                        "name": "バブルランチャー"
                    },
                    "sub": {
                        "id": "1",
                        "image_a": "/images/sub/79ec06c8afca6af0e14da4d9941706bb15f9927e.png",
                        "image_b": "/images/sub/9d6336b855940f6c8fc82979a972f9f3381c0e65.png",
                        "name": "キューバンボム"
                    },
                    "thumbnail": "/images/weapon/f296766203483ad4dc9c12604500fea5a4699b0f.png"
                }
            },
            "sort_score": 1,
            "special_count": 2
        }
    ],
    "my_team_result": {
        "key": "defeat",
        "name": "LOSE…"
    },
    "other_team_count": 99,
    "other_team_members": [
        {
            "assist_count": 5,
            "death_count": 7,
            "game_paint_point": 1287,
            "kill_count": 6,
            "player": {
                "clothes": {
                    "brand": {
                        "frequent_skill": {
                            "id": "11",
                            "image": "/images/skill/33087a476135074af856151a89a6fe4d1d3a996e.png",
                            "name": "相手インク影響軽減"
                        },
                        "id": "0",
                        "image": "/images/brand/5547e529d160b188d104e3b68ff4b7566eab9771.png",
                        "name": "バトロイカ"
                    },
                    "id": "1000",
                    "image": "/images/clothes/b6577487860b7f1458c452bf1e97b71d504b1a08.png",
                    "kind": "clothes",
                    "name": "イカホワイト",
                    "rarity": 0,
                    "thumbnail": "/images/clothes/02e3e7e8527adf5867bc8cfa808994900851b18b.png"
                },
                "clothes_skills": {
                    "main": {
                        "id": "1",
                        "image": "/images/skill/da8ff08954fd5d890fc8bc4dd4cb761e2a33b703.png",
                        "name": "インク効率アップ(サブ)"
                    },
                    "subs": [
                        {
                            "id": "1",
                            "image": "/images/skill/da8ff08954fd5d890fc8bc4dd4cb761e2a33b703.png",
                            "name": "インク効率アップ(サブ)"
                        },
                        {
                            "id": "1",
                            "image": "/images/skill/da8ff08954fd5d890fc8bc4dd4cb761e2a33b703.png",
                            "name": "インク効率アップ(サブ)"
                        },
                        {
                            "id": "1",
                            "image": "/images/skill/da8ff08954fd5d890fc8bc4dd4cb761e2a33b703.png",
                            "name": "インク効率アップ(サブ)"
                        }
                    ]
                },
                "head": {
                    "brand": {
                        "id": "98",
                        "image": "/images/brand/047cbc2f0674eeb4796efb3b6ec1b710b22d07e7.png",
                        "name": "アタリメイド"
                    },
                    "id": "27106",
                    "image": "/images/head/fb4324a76a864904c89f63d2860193ef03fdfa22.png",
                    "kind": "head",
                    "name": "グランパなアタマ",
                    "rarity": 1,
                    "thumbnail": "/images/head/77f1673b278905c70e499ac8c1b5f70ce5846678.png"
                },
                "head_skills": {
                    "main": {
                        "id": "103",
                        "image": "/images/skill/bdc5135874439cf3169d9a54b3f1fbdba3731b34.png",
                        "name": "カムバック"
                    },
                    "subs": [
                        {
                            "id": "1",
                            "image": "/images/skill/da8ff08954fd5d890fc8bc4dd4cb761e2a33b703.png",
                            "name": "インク効率アップ(サブ)"
                        },
                        {
                            "id": "1",
                            "image": "/images/skill/da8ff08954fd5d890fc8bc4dd4cb761e2a33b703.png",
                            "name": "インク効率アップ(サブ)"
                        },
                        {
                            "id": "1",
                            "image": "/images/skill/da8ff08954fd5d890fc8bc4dd4cb761e2a33b703.png",
                            "name": "インク効率アップ(サブ)"
                        }
                    ]
                },
                "nickname": "にゅた",
                "player_rank": 33,
                "player_type": {
                    "species": "inklings",
                    "style": "girl"
                },
                "principal_id": "1a1153cbdc01b111",
                "shoes": {
                    "brand": {
                        "frequent_skill": {
                            "id": "4",
                            "image": "/images/skill/d138c293c8ddac42fadf0e6531100a88c79c81f6.png",
                            "name": "イカダッシュ速度アップ"
                        },
                        "id": "2",
                        "image": "/images/brand/9ac5752790dd6dbdc7a427df95e1bfe89fe318e0.png",
                        "name": "クラーゲス"
                    },
                    "id": "2002",
                    "image": "/images/shoes/b936e1141193e2da69d5ec598d958b3fc53dd289.png",
                    "kind": "shoes",
                    "name": "キャンバスHi マッシュルーム",
                    "rarity": 0,
                    "thumbnail": "/images/shoes/5d4c87d2566d7fead24af39a313c9fc03a9aadfb.png"
                },
                "shoes_skills": {
                    "main": {
                        "id": "110",
                        "image": "/images/skill/47a74cd575b25a9de3e3592084ff3870db0cf4e0.png",
                        "name": "対物攻撃力アップ"
                    },
                    "subs": [
                        {
                            "id": "4",
                            "image": "/images/skill/d138c293c8ddac42fadf0e6531100a88c79c81f6.png",
                            "name": "イカダッシュ速度アップ"
                        },
                        {
                            "id": "4",
                            "image": "/images/skill/d138c293c8ddac42fadf0e6531100a88c79c81f6.png",
                            "name": "イカダッシュ速度アップ"
                        },
                        {
                            "id": "4",
                            "image": "/images/skill/d138c293c8ddac42fadf0e6531100a88c79c81f6.png",
                            "name": "イカダッシュ速度アップ"
                        }
                    ]
                },
                "star_rank": 2,
                "udemae": {
                    "is_x": true,
                    "name": "X",
                    "s_plus_number": null
                },
                "weapon": {
                    "id": "30",
                    "image": "/images/weapon/c6ab7ebff7af7f7604eb53a12851da880b1ec2c7.png",
                    "name": "プロモデラーMG",
                    "special": {
                        "id": "5",
                        "image_a": "/images/special/718f3506bce0bd3c17a90c45903798eb09935324.png",
                        "image_b": "/images/special/b8340ae3c4c5102a9223f84c4f92bb60ff2d0704.png",
                        "name": "カーリングボムピッチャー"
                    },
                    "sub": {
                        "id": "1",
                        "image_a": "/images/sub/79ec06c8afca6af0e14da4d9941706bb15f9927e.png",
                        "image_b": "/images/sub/9d6336b855940f6c8fc82979a972f9f3381c0e65.png",
                        "name": "キューバンボム"
                    },
                    "thumbnail": "/images/weapon/33b212a5ed9d0ab13bc06efa634ce52e8560b68b.png"
                }
            },
            "sort_score": 3,
            "special_count": 5
        },
        {
            "assist_count": 1,
            "death_count": 9,
            "game_paint_point": 1023,
            "kill_count": 9,
            "player": {
                "clothes": {
                    "brand": {
                        "frequent_skill": {
                            "id": "10",
                            "image": "/images/skill/34e114a50a001778a574f7061039d43e632137b7.png",
                            "name": "サブ性能アップ"
                        },
                        "id": "16",
                        "image": "/images/brand/de96243d58e41e928d30290162a6f496033da868.png",
                        "name": "エンペリー"
                    },
                    "id": "5032",
                    "image": "/images/clothes/fef483172222a52e036ecd443455f4d24305d2ff.png",
                    "kind": "clothes",
                    "name": "キングベンチカイザー",
                    "rarity": 2,
                    "thumbnail": "/images/clothes/7ad51daf27015aa14168448817c87a354f372021.png"
                },
                "clothes_skills": {
                    "main": {
                        "id": "3",
                        "image": "/images/skill/7de1bdfd875ef470b6066c17bed726b5b5113d48.png",
                        "name": "ヒト移動速度アップ"
                    },
                    "subs": [
                        {
                            "id": "9",
                            "image": "/images/skill/daf6883039afa62da91eb93eb2a40b673f10b715.png",
                            "name": "スーパージャンプ時間短縮"
                        },
                        {
                            "id": "8",
                            "image": "/images/skill/84ab4ba1188849dff63a4314955a53ab103b47df.png",
                            "name": "復活時間短縮"
                        },
                        {
                            "id": "6",
                            "image": "/images/skill/d83b962b84fcea9d02c591c296234f5de77f9682.png",
                            "name": "スペシャル減少量ダウン"
                        }
                    ]
                },
                "head": {
                    "brand": {
                        "frequent_skill": {
                            "id": "201",
                            "image": "/images/skill/39f3e937b709d378c178ef2bf00d9a7295b8159d.png",
                            "name": "メイン性能アップ"
                        },
                        "id": "17",
                        "image": "/images/brand/4b05e494bf9a547b4d625fd52dcdd930a6c4defc.png",
                        "name": "タタキケンサキ"
                    },
                    "id": "3017",
                    "image": "/images/head/5a106427c25247952df80e78aecf02c8d13c8c66.png",
                    "kind": "head",
                    "name": "スミガードゴーグル",
                    "rarity": 2,
                    "thumbnail": "/images/head/a4179375c31457f667dc3832dffc7b88b4f93b52.png"
                },
                "head_skills": {
                    "main": {
                        "id": "3",
                        "image": "/images/skill/7de1bdfd875ef470b6066c17bed726b5b5113d48.png",
                        "name": "ヒト移動速度アップ"
                    },
                    "subs": [
                        {
                            "id": "201",
                            "image": "/images/skill/39f3e937b709d378c178ef2bf00d9a7295b8159d.png",
                            "name": "メイン性能アップ"
                        },
                        {
                            "id": "9",
                            "image": "/images/skill/daf6883039afa62da91eb93eb2a40b673f10b715.png",
                            "name": "スーパージャンプ時間短縮"
                        },
                        {
                            "id": "255",
                            "image": "/images/skill/46f9b6fc3a2aafdc0c688dec8cadb54aa6f8ace6.png",
                            "name": "はてな"
                        }
                    ]
                },
                "nickname": "かきくけこうちゃん！",
                "player_rank": 26,
                "player_type": {
                    "species": "inklings",
                    "style": "girl"
                },
                "principal_id": "65d86a8b71ae0d2b",
                "shoes": {
                    "brand": {
                        "frequent_skill": {
                            "id": "9",
                            "image": "/images/skill/daf6883039afa62da91eb93eb2a40b673f10b715.png",
                            "name": "スーパージャンプ時間短縮"
                        },
                        "id": "1",
                        "image": "/images/brand/3d4661b3f60f4b74e9bb6760ba7397ecd2502a20.png",
                        "name": "アイロニック"
                    },
                    "id": "2012",
                    "image": "/images/shoes/86782b7bffb14d47659cc6a24a9d28e379315552.png",
                    "kind": "shoes",
                    "name": "デカロニックブラック",
                    "rarity": 1,
                    "thumbnail": "/images/shoes/57f5176aee3570a63fbeef3df6ea9bfaebf01562.png"
                },
                "shoes_skills": {
                    "main": {
                        "id": "201",
                        "image": "/images/skill/39f3e937b709d378c178ef2bf00d9a7295b8159d.png",
                        "name": "メイン性能アップ"
                    },
                    "subs": [
                        {
                            "id": "0",
                            "image": "/images/skill/04b1de71fba1f14197b9163503955c52fd74858b.png",
                            "name": "インク効率アップ(メイン)"
                        },
                        {
                            "id": "0",
                            "image": "/images/skill/04b1de71fba1f14197b9163503955c52fd74858b.png",
                            "name": "インク効率アップ(メイン)"
                        },
                        null
                    ]
                },
                "star_rank": 0,
                "udemae": {
                    "is_x": true,
                    "name": "X",
                    "s_plus_number": null
                },
                "weapon": {
                    "id": "4030",
                    "image": "/images/weapon/f208b6222acb5014ab96285e9b9a3e98039c884b.png",
                    "name": "クーゲルシュライバー",
                    "special": {
                        "id": "8",
                        "image_a": "/images/special/9871c82952ed0141be0310ace1942c9f5f66d655.png",
                        "image_b": "/images/special/26e8117808ce17dadb0f23943359e5909fef4085.png",
                        "name": "ジェットパック"
                    },
                    "sub": {
                        "id": "7",
                        "image_a": "/images/sub/7d58593453b479138bca576ea13c19b870059ce9.png",
                        "image_b": "/images/sub/9ab41340bfcef91125430d18015ccf98985efdb6.png",
                        "name": "ポイズンミスト"
                    },
                    "thumbnail": "/images/weapon/dee7a86b925710935d1ac9d3039d4867bc9ea5db.png"
                }
            },
            "sort_score": 0,
            "special_count": 1
        },
        {
            "assist_count": 8,
            "death_count": 6,
            "game_paint_point": 1602,
            "kill_count": 6,
            "player": {
                "clothes": {
                    "brand": {
                        "id": "99",
                        "image": "/images/brand/154440ecbfb65a22cdb224fac843b02cccbcad03.png",
                        "name": "amiibo"
                    },
                    "id": "25003",
                    "image": "/images/clothes/71fdc246d26adf4d38a4cad25fddab39769201ba.png",
                    "kind": "clothes",
                    "name": "スクールカーデ",
                    "rarity": 1,
                    "thumbnail": "/images/clothes/6a85b5dca811c0346cee1673975ecba198a86d91.png"
                },
                "clothes_skills": {
                    "main": {
                        "id": "3",
                        "image": "/images/skill/7de1bdfd875ef470b6066c17bed726b5b5113d48.png",
                        "name": "ヒト移動速度アップ"
                    },
                    "subs": [
                        {
                            "id": "3",
                            "image": "/images/skill/7de1bdfd875ef470b6066c17bed726b5b5113d48.png",
                            "name": "ヒト移動速度アップ"
                        },
                        {
                            "id": "3",
                            "image": "/images/skill/7de1bdfd875ef470b6066c17bed726b5b5113d48.png",
                            "name": "ヒト移動速度アップ"
                        },
                        {
                            "id": "3",
                            "image": "/images/skill/7de1bdfd875ef470b6066c17bed726b5b5113d48.png",
                            "name": "ヒト移動速度アップ"
                        }
                    ]
                },
                "head": {
                    "brand": {
                        "id": "99",
                        "image": "/images/brand/154440ecbfb65a22cdb224fac843b02cccbcad03.png",
                        "name": "amiibo"
                    },
                    "id": "25006",
                    "image": "/images/head/a0d67e44d0f17a5aa8a6256b8b9949b039df7501.png",
                    "kind": "head",
                    "name": "ヒメイトクラウン",
                    "rarity": 1,
                    "thumbnail": "/images/head/c1358f731443200f91b055a7751e6e6a3e961294.png"
                },
                "head_skills": {
                    "main": {
                        "id": "200",
                        "image": "/images/skill/0a29f0ce326a81a5ddb3a7abab1816a25fefdc7c.png",
                        "name": "爆風ダメージ軽減・改"
                    },
                    "subs": [
                        {
                            "id": "200",
                            "image": "/images/skill/0a29f0ce326a81a5ddb3a7abab1816a25fefdc7c.png",
                            "name": "爆風ダメージ軽減・改"
                        },
                        {
                            "id": "200",
                            "image": "/images/skill/0a29f0ce326a81a5ddb3a7abab1816a25fefdc7c.png",
                            "name": "爆風ダメージ軽減・改"
                        },
                        {
                            "id": "200",
                            "image": "/images/skill/0a29f0ce326a81a5ddb3a7abab1816a25fefdc7c.png",
                            "name": "爆風ダメージ軽減・改"
                        }
                    ]
                },
                "nickname": "エノシマ　ジュンコ",
                "player_rank": 63,
                "player_type": {
                    "species": "inklings",
                    "style": "girl"
                },
                "principal_id": "e893d2db3567bacb",
                "shoes": {
                    "brand": {
                        "frequent_skill": {
                            "id": "4",
                            "image": "/images/skill/d138c293c8ddac42fadf0e6531100a88c79c81f6.png",
                            "name": "イカダッシュ速度アップ"
                        },
                        "id": "2",
                        "image": "/images/brand/9ac5752790dd6dbdc7a427df95e1bfe89fe318e0.png",
                        "name": "クラーゲス"
                    },
                    "id": "23007",
                    "image": "/images/shoes/1122eec55c5125c2091e13d3cd6308938470ee6c.png",
                    "kind": "shoes",
                    "name": "ミッドナイトスリッポン",
                    "rarity": 2,
                    "thumbnail": "/images/shoes/4267491aebf9fd7a84d3d7654286b3197cf7bb2b.png"
                },
                "shoes_skills": {
                    "main": {
                        "id": "110",
                        "image": "/images/skill/47a74cd575b25a9de3e3592084ff3870db0cf4e0.png",
                        "name": "対物攻撃力アップ"
                    },
                    "subs": [
                        {
                            "id": "8",
                            "image": "/images/skill/84ab4ba1188849dff63a4314955a53ab103b47df.png",
                            "name": "復活時間短縮"
                        },
                        {
                            "id": "11",
                            "image": "/images/skill/33087a476135074af856151a89a6fe4d1d3a996e.png",
                            "name": "相手インク影響軽減"
                        },
                        {
                            "id": "255",
                            "image": "/images/skill/46f9b6fc3a2aafdc0c688dec8cadb54aa6f8ace6.png",
                            "name": "はてな"
                        }
                    ]
                },
                "star_rank": 1,
                "udemae": {
                    "is_x": true,
                    "name": "X",
                    "s_plus_number": null
                },
                "weapon": {
                    "id": "10",
                    "image": "/images/weapon/91b6666bcbfccc204d86f21222a8db22a27d08d0.png",
                    "name": "わかばシューター",
                    "special": {
                        "id": "1",
                        "image_a": "/images/special/abe458a7d13d855f1b27135ccf3e96f46f1f3d10.png",
                        "image_b": "/images/special/415bf85acb0b0dcc478316332fe86efb1fe4f203.png",
                        "name": "インクアーマー"
                    },
                    "sub": {
                        "id": "0",
                        "image_a": "/images/sub/d2eaeec524d28ef315a13f8a9e11dd1039cb78aa.png",
                        "image_b": "/images/sub/b13bf755b279af83904892fae01cd98c866dfec7.png",
                        "name": "スプラッシュボム"
                    },
                    "thumbnail": "/images/weapon/f1419d88f30dfacdb94a8122ccdd8c14bbadc7c4.png"
                }
            },
            "sort_score": 2,
            "special_count": 7
        },
        {
            "assist_count": 1,
            "death_count": 9,
            "game_paint_point": 902,
            "kill_count": 9,
            "player": {
                "clothes": {
                    "brand": {
                        "frequent_skill": {
                            "id": "201",
                            "image": "/images/skill/39f3e937b709d378c178ef2bf00d9a7295b8159d.png",
                            "name": "メイン性能アップ"
                        },
                        "id": "17",
                        "image": "/images/brand/4b05e494bf9a547b4d625fd52dcdd930a6c4defc.png",
                        "name": "タタキケンサキ"
                    },
                    "id": "7009",
                    "image": "/images/clothes/9e2ed26da468aa39f194e996f21e6a75c534c148.png",
                    "kind": "clothes",
                    "name": "ドロップスウェット ポジ",
                    "rarity": 2,
                    "thumbnail": "/images/clothes/5bdb11527bcdfb1722540dd306abe64319f4f113.png"
                },
                "clothes_skills": {
                    "main": {
                        "id": "4",
                        "image": "/images/skill/d138c293c8ddac42fadf0e6531100a88c79c81f6.png",
                        "name": "イカダッシュ速度アップ"
                    },
                    "subs": [
                        {
                            "id": "201",
                            "image": "/images/skill/39f3e937b709d378c178ef2bf00d9a7295b8159d.png",
                            "name": "メイン性能アップ"
                        },
                        {
                            "id": "201",
                            "image": "/images/skill/39f3e937b709d378c178ef2bf00d9a7295b8159d.png",
                            "name": "メイン性能アップ"
                        },
                        {
                            "id": "201",
                            "image": "/images/skill/39f3e937b709d378c178ef2bf00d9a7295b8159d.png",
                            "name": "メイン性能アップ"
                        }
                    ]
                },
                "head": {
                    "brand": {
                        "frequent_skill": {
                            "id": "8",
                            "image": "/images/skill/84ab4ba1188849dff63a4314955a53ab103b47df.png",
                            "name": "復活時間短縮"
                        },
                        "id": "7",
                        "image": "/images/brand/8175954b5a7e02b8097dbb484c808c8f39d31f41.png",
                        "name": "ホタックス"
                    },
                    "id": "2011",
                    "image": "/images/head/29a325171dc2c8df76d99502c58c42f9337aafb8.png",
                    "kind": "head",
                    "name": "オシノビニット",
                    "rarity": 1,
                    "thumbnail": "/images/head/fab0df87794c055431e03d12543972a092840b5c.png"
                },
                "head_skills": {
                    "main": {
                        "id": "4",
                        "image": "/images/skill/d138c293c8ddac42fadf0e6531100a88c79c81f6.png",
                        "name": "イカダッシュ速度アップ"
                    },
                    "subs": [
                        {
                            "id": "201",
                            "image": "/images/skill/39f3e937b709d378c178ef2bf00d9a7295b8159d.png",
                            "name": "メイン性能アップ"
                        },
                        {
                            "id": "201",
                            "image": "/images/skill/39f3e937b709d378c178ef2bf00d9a7295b8159d.png",
                            "name": "メイン性能アップ"
                        },
                        {
                            "id": "201",
                            "image": "/images/skill/39f3e937b709d378c178ef2bf00d9a7295b8159d.png",
                            "name": "メイン性能アップ"
                        }
                    ]
                },
                "nickname": "s",
                "player_rank": 98,
                "player_type": {
                    "species": "inklings",
                    "style": "girl"
                },
                "principal_id": "e97b229cc248649c",
                "shoes": {
                    "brand": {
                        "frequent_skill": {
                            "id": "4",
                            "image": "/images/skill/d138c293c8ddac42fadf0e6531100a88c79c81f6.png",
                            "name": "イカダッシュ速度アップ"
                        },
                        "id": "2",
                        "image": "/images/brand/9ac5752790dd6dbdc7a427df95e1bfe89fe318e0.png",
                        "name": "クラーゲス"
                    },
                    "id": "2005",
                    "image": "/images/shoes/ff7cec267fe1d92dad171a3bd6f9a03bc7f9ad5c.png",
                    "kind": "shoes",
                    "name": "キャンバスHi トマト",
                    "rarity": 1,
                    "thumbnail": "/images/shoes/824d10ec463333bfa4a495bb70adb30110136913.png"
                },
                "shoes_skills": {
                    "main": {
                        "id": "11",
                        "image": "/images/skill/33087a476135074af856151a89a6fe4d1d3a996e.png",
                        "name": "相手インク影響軽減"
                    },
                    "subs": [
                        {
                            "id": "7",
                            "image": "/images/skill/f20a3e85feeb6b4bb021d28059afd6265cee0b43.png",
                            "name": "スペシャル性能アップ"
                        },
                        {
                            "id": "7",
                            "image": "/images/skill/f20a3e85feeb6b4bb021d28059afd6265cee0b43.png",
                            "name": "スペシャル性能アップ"
                        },
                        {
                            "id": "8",
                            "image": "/images/skill/84ab4ba1188849dff63a4314955a53ab103b47df.png",
                            "name": "復活時間短縮"
                        }
                    ]
                },
                "star_rank": 2,
                "udemae": {
                    "is_x": true,
                    "name": "X",
                    "s_plus_number": null
                },
                "weapon": {
                    "id": "41",
                    "image": "/images/weapon/331d889d8113b794131080c8943e05a3d2c4547d.png",
                    "name": "スプラシューターコラボ",
                    "special": {
                        "id": "8",
                        "image_a": "/images/special/9871c82952ed0141be0310ace1942c9f5f66d655.png",
                        "image_b": "/images/special/26e8117808ce17dadb0f23943359e5909fef4085.png",
                        "name": "ジェットパック"
                    },
                    "sub": {
                        "id": "0",
                        "image_a": "/images/sub/d2eaeec524d28ef315a13f8a9e11dd1039cb78aa.png",
                        "image_b": "/images/sub/b13bf755b279af83904892fae01cd98c866dfec7.png",
                        "name": "スプラッシュボム"
                    },
                    "thumbnail": "/images/weapon/5f519a8b3f436c854dc81ee14bfc3a26aef09ebc.png"
                }
            },
            "sort_score": 1,
            "special_count": 3
        }
    ],
    "other_team_result": {
        "key": "victory",
        "name": "WIN!"
    },
    "player_rank": 44,
    "player_result": {
        "assist_count": 3,
        "death_count": 8,
        "game_paint_point": 1262,
        "kill_count": 5,
        "player": {
            "clothes": {
                "brand": {
                    "frequent_skill": {
                        "id": "9",
                        "image": "/images/skill/daf6883039afa62da91eb93eb2a40b673f10b715.png",
                        "name": "スーパージャンプ時間短縮"
                    },
                    "id": "1",
                    "image": "/images/brand/3d4661b3f60f4b74e9bb6760ba7397ecd2502a20.png",
                    "name": "アイロニック"
                },
                "id": "1031",
                "image": "/images/clothes/19f7a97d7c979843fcb94935707e0b76ca323643.png",
                "kind": "clothes",
                "name": "デカロゴＴ シロ",
                "rarity": 0,
                "thumbnail": "/images/clothes/28d03e319cb5086d23ba8d9844241a18cd388a90.png"
            },
            "clothes_skills": {
                "main": {
                    "id": "11",
                    "image": "/images/skill/33087a476135074af856151a89a6fe4d1d3a996e.png",
                    "name": "相手インク影響軽減"
                },
                "subs": [
                    {
                        "id": "3",
                        "image": "/images/skill/7de1bdfd875ef470b6066c17bed726b5b5113d48.png",
                        "name": "ヒト移動速度アップ"
                    },
                    {
                        "id": "3",
                        "image": "/images/skill/7de1bdfd875ef470b6066c17bed726b5b5113d48.png",
                        "name": "ヒト移動速度アップ"
                    },
                    {
                        "id": "3",
                        "image": "/images/skill/7de1bdfd875ef470b6066c17bed726b5b5113d48.png",
                        "name": "ヒト移動速度アップ"
                    }
                ]
            },
            "head": {
                "brand": {
                    "id": "98",
                    "image": "/images/brand/047cbc2f0674eeb4796efb3b6ec1b710b22d07e7.png",
                    "name": "アタリメイド"
                },
                "id": "27106",
                "image": "/images/head/fb4324a76a864904c89f63d2860193ef03fdfa22.png",
                "kind": "head",
                "name": "グランパなアタマ",
                "rarity": 1,
                "thumbnail": "/images/head/77f1673b278905c70e499ac8c1b5f70ce5846678.png"
            },
            "head_skills": {
                "main": {
                    "id": "103",
                    "image": "/images/skill/bdc5135874439cf3169d9a54b3f1fbdba3731b34.png",
                    "name": "カムバック"
                },
                "subs": [
                    {
                        "id": "10",
                        "image": "/images/skill/34e114a50a001778a574f7061039d43e632137b7.png",
                        "name": "サブ性能アップ"
                    },
                    {
                        "id": "200",
                        "image": "/images/skill/0a29f0ce326a81a5ddb3a7abab1816a25fefdc7c.png",
                        "name": "爆風ダメージ軽減・改"
                    },
                    {
                        "id": "10",
                        "image": "/images/skill/34e114a50a001778a574f7061039d43e632137b7.png",
                        "name": "サブ性能アップ"
                    }
                ]
            },
            "nickname": "ちゅーたな",
            "player_rank": 44,
            "player_type": {
                "species": "octolings",
                "style": "girl"
            },
            "principal_id": "fb9a41e92d348bb7",
            "shoes": {
                "brand": {
                    "frequent_skill": {
                        "id": "4",
                        "image": "/images/skill/d138c293c8ddac42fadf0e6531100a88c79c81f6.png",
                        "name": "イカダッシュ速度アップ"
                    },
                    "id": "2",
                    "image": "/images/brand/9ac5752790dd6dbdc7a427df95e1bfe89fe318e0.png",
                    "name": "クラーゲス"
                },
                "id": "4000",
                "image": "/images/shoes/c04a1ffdbea45f728f65fca0ca7142cd38cedfe8.png",
                "kind": "shoes",
                "name": "オイスタークロッグ",
                "rarity": 0,
                "thumbnail": "/images/shoes/19feeb268c95dae1e47b53617e5784809c571a10.png"
            },
            "shoes_skills": {
                "main": {
                    "id": "109",
                    "image": "/images/skill/8a3f06a972689b094f762626ff36b3db8ee545b5.png",
                    "name": "ステルスジャンプ"
                },
                "subs": [
                    {
                        "id": "8",
                        "image": "/images/skill/84ab4ba1188849dff63a4314955a53ab103b47df.png",
                        "name": "復活時間短縮"
                    },
                    {
                        "id": "8",
                        "image": "/images/skill/84ab4ba1188849dff63a4314955a53ab103b47df.png",
                        "name": "復活時間短縮"
                    },
                    {
                        "id": "8",
                        "image": "/images/skill/84ab4ba1188849dff63a4314955a53ab103b47df.png",
                        "name": "復活時間短縮"
                    }
                ]
            },
            "star_rank": 1,
            "udemae": {
                "is_number_reached": true,
                "is_x": true,
                "name": "X",
                "number": 128,
                "s_plus_number": null
            },
            "weapon": {
                "id": "60",
                "image": "/images/weapon/1f2b1db5917ef7a4e62f0e15b8805275e33f2179.png",
                "name": "N-ZAP85",
                "special": {
                    "id": "1",
                    "image_a": "/images/special/abe458a7d13d855f1b27135ccf3e96f46f1f3d10.png",
                    "image_b": "/images/special/415bf85acb0b0dcc478316332fe86efb1fe4f203.png",
                    "name": "インクアーマー"
                },
                "sub": {
                    "id": "1",
                    "image_a": "/images/sub/79ec06c8afca6af0e14da4d9941706bb15f9927e.png",
                    "image_b": "/images/sub/9d6336b855940f6c8fc82979a972f9f3381c0e65.png",
                    "name": "キューバンボム"
                },
                "thumbnail": "/images/weapon/fdcd7cbe806eb84df374ea8f7e074ac9637d4762.png"
            }
        },
        "sort_score": 2,
        "special_count": 4
    },
    "rank": null,
    "rule": {
        "key": "rainmaker",
        "multiline_name": "ガチホコ\nバトル",
        "name": "ガチホコバトル"
    },
    "stage": {
        "id": "16",
        "image": "/images/stage/e4c4800be9fff23112334b193abb0fdf36e05933.png",
        "name": "モンガラキャンプ場"
    },
    "star_rank": 1,
    "start_time": 1573268451,
    "type": "gachi",
    "udemae": {
        "is_number_reached": true,
        "is_x": true,
        "name": "X",
        "number": 128,
        "s_plus_number": null
    },
    "weapon_paint_point": 3080771,
    "x_power": 2375.1
}